[
  {
    "Item1": "01-Adi Parva",
    "Item2": 54.386839481555342
  },
  {
    "Item1": "02-Sabha Parva",
    "Item2": 53.895582329317271
  },
  {
    "Item1": "03-Vana Parva",
    "Item2": 56.069609507640074
  },
  {
    "Item1": "04-Virata Parva",
    "Item2": 48.766447368421048
  },
  {
    "Item1": "05-Udyoga Parva",
    "Item2": 54.713006845708264
  },
  {
    "Item1": "06-Bhishma Parva",
    "Item2": 55.507559395248386
  },
  {
    "Item1": "07-Drona Parva",
    "Item2": 52.937420178799485
  },
  {
    "Item1": "08-Karna Parva",
    "Item2": 56.547122602168479
  },
  {
    "Item1": "09-Shalya Parva",
    "Item2": 56.80304471931494
  },
  {
    "Item1": "10-Sauptika Parva",
    "Item2": 63.022508038585215
  },
  {
    "Item1": "11-Stri Parva",
    "Item2": 56.4625850340136
  },
  {
    "Item1": "12-Shanti Parva",
    "Item2": 56.503280586646085
  },
  {
    "Item1": "13-Anushasana Parva",
    "Item2": 55.005268703898849
  },
  {
    "Item1": "14-Ashvamedhika Parva",
    "Item2": 50.112866817155755
  },
  {
    "Item1": "15-Ashramavasika Parva",
    "Item2": 45.586297760210805
  },
  {
    "Item1": "16-Mausala Parva",
    "Item2": 59.327217125382262
  },
  {
    "Item1": "17-Mahaprasthanika Parva",
    "Item2": 55.70469798657718
  },
  {
    "Item1": "18-Svargarohana Parva",
    "Item2": 47.535211267605632
  }
]
