[
  {
    "Item1": "01-Adi Parva",
    "Item2": 73.114495479643224
  },
  {
    "Item1": "02-Sabha Parva",
    "Item2": 135.30547658638631
  },
  {
    "Item1": "03-Vana Parva",
    "Item2": 61.0898802087161
  },
  {
    "Item1": "04-Virata Parva",
    "Item2": 162.122679708465
  },
  {
    "Item1": "05-Udyoga Parva",
    "Item2": 85.103475102371235
  },
  {
    "Item1": "06-Bhishma Parva",
    "Item2": 74.9455391622933
  },
  {
    "Item1": "07-Drona Parva",
    "Item2": 53.27495997425639
  },
  {
    "Item1": "08-Karna Parva",
    "Item2": 81.557694115265321
  },
  {
    "Item1": "09-Shalya Parva",
    "Item2": 108.47738781211804
  },
  {
    "Item1": "10-Sauptika Parva",
    "Item2": 286.51554101425563
  },
  {
    "Item1": "11-Stri Parva",
    "Item2": 253.58676779676503
  },
  {
    "Item1": "12-Shanti Parva",
    "Item2": 39.430751140901585
  },
  {
    "Item1": "13-Anushasana Parva",
    "Item2": 48.991325633902392
  },
  {
    "Item1": "14-Ashvamedhika Parva",
    "Item2": 121.4982547212029
  },
  {
    "Item1": "15-Ashramavasika Parva",
    "Item2": 182.85051436246528
  },
  {
    "Item1": "16-Mausala Parva",
    "Item2": 385.13596653131538
  },
  {
    "Item1": "17-Mahaprasthanika Parva",
    "Item2": 440.93981332475056
  },
  {
    "Item1": "18-Svargarohana Parva",
    "Item2": 249.9712014744845
  }
]
